Calculator/Calculator.py
Calculator/__init__.py
Calculator_tvaino-0.0.14.dist-info/LICENSE
Calculator_tvaino-0.0.14.dist-info/METADATA
Calculator_tvaino-0.0.14.dist-info/WHEEL
Calculator_tvaino-0.0.14.dist-info/top_level.txt
Calculator_tvaino-0.0.14.dist-info/RECORD
