Metadata-Version: 2.1
Name: Calculator_tvaino
Version: 0.0.14
Summary: Basic arithmetic operations
Author-email: Tomas Vainoras <vainoras@gmail.com>
Project-URL: Homepage, https://github.com/TuringCollegeSubmissions/tvaino-DWWP.1.5/tree/master/Calculator_pack
Classifier: Programming Language :: Python :: 3
Classifier: License :: OSI Approved :: MIT License
Classifier: Operating System :: OS Independent
Requires-Python: >=3.8
License-File: LICENSE
